oplnk_python_utils/__init__.py
oplnk_python_utils/cache/__init__.py
oplnk_python_utils/cache/cache_utils.py
oplnk_python_utils/core/__init__.py
oplnk_python_utils/core/data.py
oplnk_python_utils/core/parsing.py
oplnk_python_utils/core/serialization.py
oplnk_python_utils/query/__init__.py
oplnk_python_utils/query/query_builder.py
oplnk_python_utils/reports/__init__.py
oplnk_python_utils-1.1.9.dist-info/licenses/LICENSE
oplnk_python_utils-1.1.9.dist-info/METADATA
oplnk_python_utils-1.1.9.dist-info/WHEEL
oplnk_python_utils-1.1.9.dist-info/top_level.txt
oplnk_python_utils-1.1.9.dist-info/RECORD
